MANIFEST.in
README.rst
setup.py
QuoteOfTheDay.egg-info/PKG-INFO
QuoteOfTheDay.egg-info/SOURCES.txt
QuoteOfTheDay.egg-info/dependency_links.txt
QuoteOfTheDay.egg-info/entry_points.txt
QuoteOfTheDay.egg-info/top_level.txt
qotd/__init__.py
qotd/qotd.py